odoo10_addon_purchase_picking_state-10.0.1.0.0-py2.7-nspkg.pth
odoo10_addon_purchase_picking_state-10.0.1.0.0.dist-info/top_level.txt
odoo10_addon_purchase_picking_state-10.0.1.0.0.dist-info/WHEEL
odoo10_addon_purchase_picking_state-10.0.1.0.0.dist-info/RECORD
odoo10_addon_purchase_picking_state-10.0.1.0.0.dist-info/metadata.json
odoo10_addon_purchase_picking_state-10.0.1.0.0.dist-info/DESCRIPTION.rst
odoo10_addon_purchase_picking_state-10.0.1.0.0.dist-info/METADATA
odoo10_addon_purchase_picking_state-10.0.1.0.0.dist-info/namespace_packages.txt
odoo/addons/purchase_picking_state/__manifest__.py
odoo/addons/purchase_picking_state/purchase.py
odoo/addons/purchase_picking_state/purchase_view.xml
odoo/addons/purchase_picking_state/__init__.py
odoo/addons/purchase_picking_state/README.rst
odoo/addons/purchase_picking_state/i18n/de.po
odoo/addons/purchase_picking_state/i18n/fr.po
odoo/addons/purchase_picking_state/i18n/pt_BR.po
odoo/addons/purchase_picking_state/tests/test_purchase_picking_state.py
odoo/addons/purchase_picking_state/tests/__init__.py
odoo/addons/purchase_picking_state/static/description/icon.png
