Metadata-Version: 2.0
Name: odoo10-addon-purchase-picking-state
Version: 10.0.1.0.0
Summary: Add the status of all the incoming picking in the purchase order
Home-page: http://akretion.com
Author: Akretion
Author-email: UNKNOWN
License: AGPL-3
Platform: UNKNOWN
Requires-Dist: odoo (<10.1dev,>=10.0)
Classifier: Programming Language :: Python :: 2.7
Classifier: Framework :: Odoo
Classifier: License :: OSI Approved :: GNU Affero General Public License v3
